{
	"format_version": "1.12.0",
	"minecraft:geometry": [
		{
			"description": {
				"identifier": "geometry.chicken.cold",
				"texture_width": 64,
				"texture_height": 64,
				"visible_bounds_width": 3,
				"visible_bounds_height": 2.25,
				"visible_bounds_offset": [0, 0.875, 0]
			},
			"bones": [
				{
					"name": "body",
					"pivot": [0, 8, 0],
					"cubes": [
						{"origin": [-3, 11, -11], "size": [6, 7, 7], "pivot": [0, 8, -7], "rotation": [-90, 0, 180], "uv": [0, 0]},
						{"origin": [-1.5, 12, -16], "size": [5, 3, 5], "pivot": [0.5, 3, -13], "rotation": [-120, 0, 180], "uv": [4, 2]},
						{"origin": [-3, 12, -3.1], "size": [6, 1, 5.1], "pivot": [0, 8, -1], "rotation": [-90, 0, 0], "uv": [26, 15]}
					]
				},
				{
					"name": "body4",
					"parent": "body",
					"pivot": [0, 7, -10],
					"rotation": [17.5, 0, 0],
					"cubes": [
						{"origin": [-2, 12, -13], "size": [4, 4, 5], "pivot": [0, 7, -10], "rotation": [-90, 0, 0], "uv": [3, 17]}
					]
				},
				{
					"name": "body2",
					"parent": "body",
					"pivot": [0, 6, 1],
					"rotation": [35, 0, 0],
					"cubes": [
						{"origin": [-3, 9, 0.5], "size": [6, 2, 5], "pivot": [0, 7, 2.5], "rotation": [-70, 0, 180], "uv": [24, 21]},
						{"origin": [-0.0812, 6.67173, 5.24558], "size": [0, 7, 6], "pivot": [-0.5, 8, 8], "rotation": [-93.90399, 17.07228, -13.08619], "uv": [26, 0]},
						{"origin": [0.0812, 6.67173, 4.24558], "size": [0, 8, 6], "pivot": [0.5, 8, 7], "rotation": [-93.90399, -17.07228, 13.08619], "uv": [26, 0], "mirror": true},
						{"origin": [-2.9188, 3.67173, -0.75442], "size": [0, 6, 4], "pivot": [-2.5, 5, 2], "rotation": [-86.09601, 17.07228, -166.91381], "uv": [28, 2], "mirror": true},
						{"origin": [2.9188, 3.67173, -0.75442], "size": [0, 6, 4], "pivot": [2.5, 5, 2], "rotation": [-86.09601, -17.07228, 166.91381], "uv": [28, 2]},
						{"origin": [-0.0812, 4.67173, 3.64558], "size": [0, 6, 5], "pivot": [-0.5, 6, 6.4], "rotation": [85.92777, 82.68019, -93.75131], "uv": [26, 0]}
					]
				},
				{
					"name": "body3",
					"parent": "body2",
					"pivot": [0, 7.4, 6],
					"rotation": [15, 0, 0],
					"cubes": [
						{"origin": [-2, 7.19117, 4.42326], "size": [4, 2, 2], "pivot": [0, 6.6, 5.3], "rotation": [-90, 0, 180], "uv": [30, 40]}
					]
				},
				{
					"name": "head",
					"pivot": [0, 10, -5],
					"cubes": [
						{"origin": [-2, 11.4, -5.5], "size": [4, 4, 3], "uv": [38, 0]},
						{"origin": [0, 9.4, -6.5], "size": [0, 7, 6], "uv": [0, 27]}
					],
					"locators": {
						"lead": [0, 10, -5]
					}
				},
				{
					"name": "comb",
					"parent": "head",
					"pivot": [0, 10, -5],
					"cubes": [
						{"origin": [-1, 11.4, -6.5], "size": [2, 1, 2], "uv": [14, 26]}
					]
				},
				{
					"name": "beak",
					"parent": "head",
					"pivot": [0, 10, -5],
					"cubes": [
						{"origin": [-1, 12.4, -7.5], "size": [2, 1, 2], "uv": [42, 36]}
					]
				},
				{
					"name": "leg0",
					"pivot": [-2, 5, 1],
					"cubes": [
						{"origin": [-3.5, 2, -1], "size": [2.5, 3, 3], "uv": [42, 30], "mirror": true},
						{"origin": [-4, 0, -3], "size": [4, 0, 4], "uv": [38, 9]},
						{"origin": [-3, 0, 0], "size": [2, 4, 1], "uv": [42, 43], "mirror": true}
					]
				},
				{
					"name": "leg1",
					"pivot": [1, 5, 1],
					"cubes": [
						{"origin": [1, 2, -1], "size": [2.5, 3, 3], "uv": [42, 30]},
						{"origin": [1, 0, 0], "size": [2, 4, 1], "uv": [42, 43]},
						{"origin": [0, 0, -3], "size": [4, 0, 4], "uv": [14, 40]}
					]
				},
				{
					"name": "wing0",
					"pivot": [-3, 11, 0],
					"cubes": [
						{"origin": [-4, 5, -3], "size": [1, 5, 6], "pivot": [0, 0, 0], "rotation": [7.5, 0, 0], "uv": [28, 30], "mirror": true}
					]
				},
				{
					"name": "wing1",
					"pivot": [3, 11, 0],
					"cubes": [
						{"origin": [3, 5, -3], "size": [1, 5, 6], "pivot": [0, 0, 0], "rotation": [7.5, 0, 0], "uv": [28, 30]}
					]
				}
			]
		}
	]
}